<?xml version="1.0" encoding="utf-8"?>
<!--
    Copyright © 2020 SpiceOS Project

    Licensed under the Apache License, Version 2.0 (the "License");
    you may not use this file except in compliance with the License.
    You may obtain a copy of the License at

    http://www.apache.org/licenses/LICENSE-2.0

    Unless required by applicable law or agreed to in writing, software
    distributed under the License is distributed on an "AS IS" BASIS,
    WITHOUT WARRANTIES OR CONDITIONS OF ANY KIND, either express or implied.
    See the License for the specific language governing permissions and
    limitations under the License.
-->

<resources xmlns:xliff="urn:oasis:names:tc:xliff:document:1.2">

    <!-- SpiceOS -->
    <string name="spiceos_settings_title">SpiceOS Settings</string>
    <string name="spiceos_dashboard_summary"></string>
    <string name="spiceos_about_info">About SpiceOS</string>
    <string name="spiceos_about_info_summary_title">About Community</string>
    <string name="spiceos_about_info_summary">LineageOS Based with more tweaks</string>

    <!-- Dev Info -->
    <string name="devs_header">Developers</string>
    <string name="dev_1">Mohammed Althaf</string>
    <string name="dev_1_git">althafvly</string>
    <string name="dev1_description">Core Developer</string>
    <string name="dev_2">Anush Madathumkara</string>
    <string name="dev_2_git">Anush02198</string>
    <string name="dev2_description">Core Developer</string>
    <string name="dev_3">Aswin A.S</string>
    <string name="dev_3_git">aswin7469</string>
    <string name="dev3_description">Core Developer</string>
    <string name="dev_4">Vivek Achooz</string>
    <string name="dev_4_git">vivekachooz</string>
    <string name="dev4_description">Core Developer</string>
    <string name="dev_5">Jijin Raj</string>
    <string name="dev_5_git">G-H-O-5-T</string>
    <string name="dev5_description">Group Manager</string>
    <string name="dev_6">Teenu Kumar</string>
    <string name="dev_6_git">teenukumar123</string>
    <string name="dev6_description">Designer</string>
    <string name="dev_7">Suneesh</string>
    <string name="dev_7_git">kalmin06</string>
    <string name="dev7_description">Group Manager</string>
    <string name="dev_8">Joshua</string>
    <string name="dev_8_git">axewolf21</string>
    <string name="dev8_description">Group Manager</string>

    <!-- Mentions -->
    <string name="mentions_header">Honorable Mentions</string>
    <string name="mentions1">SpiceOS Community</string>
    <string name="mentions1_git">SpiceOS</string>
    <string name="mentions1_description">Our Strength</string>

    <!-- Maintainer Info -->
    <string name="maintainers_header">Maintainers</string>
    <string name="co_maintainers_header">Co-Maintainers</string>
    <string name="maintainers_header_summary">These are the Official Devices Maintainers...</string>
    <string name="device_maintainers"></string>
    <string name="device_jasmine_sprout">MI A2</string>
    <string name="device_jasmine_sprout_description">jasmine_sprout\nAnush02198</string>
    <string name="device_osprey">Moto G 2015</string>
    <string name="device_osprey_description">osprey\nalthafvly</string>

    <!-- Categories -->
    <string name="gestures_title">Gestures</string>
    <string name="gestures_summary">Customize gestures</string>
    <string name="lockscreen_title">Lock Screen</string>
    <string name="lockscreen_summary">Make lockscreen Sessy</string>
    <string name="misc_title">Miscellaneous</string>
    <string name="misc_summary">Some useless stuff</string>
    <string name="powermenu_title">Power Menu</string>
    <string name="powermenu_summary">Death sentences</string>
    <string name="quicksettings_title">Quick Settings</string>
    <string name="quicksettings_summary">Customize QS</string>
    <string name="nav_title">Navigation Settings</string>
    <string name="nav_summary">Make navigation look cool</string>
    <string name="statusbar_title">Status Bar</string>
    <string name="statusbar_summary">Customize statusbar</string>
    <string name="notifications_title">Notifications</string>
    <string name="notifications_summary">Cool Notification stuff</string>

    <!-- General strings -->
    <string name="ok">OK</string>
    <string name="reset">Reset</string>
    <string name="cancel">Cancel</string>
    <string name="save">Save</string>

    <!-- Color Picker -->
    <string name="dialog_color_picker">Color Picker</string>
    <string name="press_color_to_apply">Press on color below to apply</string>
    <string name="arrow_right">→</string>
    <string name="arrow_down">↓</string>
    <string name="hex">Hex:</string>
    <string name="hex_hint">#ff000000</string>
    <string name="set">Set</string>
    <string name="color_default">Default</string>

    <!-- Units -->
    <string name="unit_seconds">seconds</string>
    <string name="unit_milliseconds">milliseconds</string>
    <string name="unit_pixels">dp</string>

    <!-- Custom seekbar -->
    <string name="custom_seekbar_value">Value: <xliff:g id="v">%s</xliff:g></string>
    <string name="custom_seekbar_default_value">by default</string>
    <string name="custom_seekbar_default_value_to_set">Default value: <xliff:g id="v">%s</xliff:g>\nLong tap to set</string>
    <string name="custom_seekbar_default_value_is_set">Default value is set</string>

    <!-- Bluetooth status -->
    <string name="bluetooth_battery_title">Bluetooth battery status</string>
    <string name="bluetooth_battery_summary">Display battery status for the connected bluetooth device, if available</string>

    <!--VoLTE Icon Switch-->
     <string name="volte_icon_title">VoLTE icon</string>
     <string name="status_bar_volte_disabled">Disabled</string>
     <string name="status_bar_volte_style_1">Bliss Style</string>
     <string name="status_bar_volte_style_2">Sony</string>
     <string name="status_bar_volte_style_3">Pill shape</string>
     <string name="status_bar_volte_style_4">Square 2 tone</string>
     <string name="status_bar_volte_style_5">Oneplus</string>
     <string name="status_bar_volte_style_6">Notch friendly</string>
     <string name="status_bar_volte_style_7">Just an Icon</string>
     <string name="status_bar_volte_style_8">EMUI</string>
     <string name="status_bar_volte_style_9">Oneplus Compact</string>
     <string name="status_bar_volte_style_10">Spice Volte</string>

     <!-- Roaming indicator icon -->
     <string name="roaming_indicator_icon_title">Roaming indicator</string>
     <string name="roaming_indicator_icon_summary">Display roaming indicator in signal icon when in roaming mode</string>

     <!-- 4G icon -->
     <string name="show_fourg_icon_title">4G icon</string>
     <string name="show_fourg_icon_summary">Display 4G icon in signal icon instead LTE</string>

     <!-- Lockscreen battery info indicator  -->
     <string name="lockscreen_battery_info_title">Lockscreen charging info</string>
     <string name="lockscreen_battery_info_summary">Display negociated charger max current and voltage and battery temperature on lockscreen while charging</string>

     <!-- Quick settings tiles -->
     <string name="qs_rows_portrait_title">Rows (portrait)</string>
     <string name="qs_rows_landscape_title">Rows (landscape)</string>
     <string name="qs_columns_portrait_title">Columns (portrait)</string>
     <string name="qs_columns_landscape_title">Columns (landscape)</string>

     <!-- QS Tile title visibility -->
     <string name="qs_tile_title_visibility_title">Tile title</string>
     <string name="qs_tile_title_visibility_summary">Display title below each tile</string>

     <!-- VoWiFi icon -->
      <string name="vowifi_icon_title">VoWiFi icon style</string>
      <string name="vowifi_icon_summary">Display VoWiFi icon when available</string>
      <string name="vowifi_icon_disabled">Disabled</string>
      <string name="vowifi_icon_default">Oneplus</string>
      <string name="vowifi_icon_moto">Motorola</string>
      <string name="vowifi_icon_asus">Asus</string>
      <string name="vowifi_icon_emui">Emui</string>
      <string name="vowifi_icon_oneplus_compact">Oneplus Compact</string>
      <string name="volte_vowifi_override_title">VoWiFi override</string>
      <string name="volte_vowifi_override_summary">Hide VoLTE when VoWiFi is available. This also overrides old style signal icon for VoWiFi.</string>

      <!-- QS Lock Icon -->
      <string name="lockscreen_lock_icon_title">Lock icon</string>
      <string name="lockscreen_lock_icon_summary">Display lock icon on the lockscreen</string>

      <!-- Quick settings haptic feedback -->
      <string name="quick_settings_vibrate_title">Vibrate on touch</string>
      <string name="quick_settings_vibrate_summary">Vibrate when touching tiles</string>

</resources>
